hidden_text/__init__.py
hidden_text/unix_impl.py
hidden_text/windows_impl.py
hidden_text-0.1.0.dist-info/licenses/LICENSE
hidden_text-0.1.0.dist-info/METADATA
hidden_text-0.1.0.dist-info/WHEEL
hidden_text-0.1.0.dist-info/top_level.txt
hidden_text-0.1.0.dist-info/RECORD
